grappler/__init__.py
grappler/_hook.py
grappler/_types.py
grappler/grapplers/__init__.py
grappler/grapplers/_bouncer.py
grappler/grapplers/_composite.py
grappler/grapplers/_entry_point.py
grappler/grapplers/_list.py
grappler/grapplers/_static.py
grappler/grapplers/bases/__init__.py
grappler/grapplers/bases/_basic.py
grappler/grapplers/bases/_plugin_pair.py
grappler-0.1.1.dist-info/WHEEL
grappler-0.1.1.dist-info/METADATA
grappler-0.1.1.dist-info/license_files/COPYING
grappler-0.1.1.dist-info/RECORD
