Metadata-Version: 2.1
Name: grappler
Version: 0.1.1
Summary: Load plugins into Python apps
License: GPLv3
Author-email: Te-je Rodgers <tjd.rodgers@gmail.com>
Requires-Python: >=3.8
Requires-Dist: importlib-metadata>=4.12.0
Requires-Dist: typing-extensions>=4.3.0
Project-URL: Documentation, https://mr-rodgers.github.io/grappler/
Project-URL: Repository, https://github.com/mr-rodgers/grappler
